pyxel_input_manager/__init__.py
pyxel_input_manager/__main__.py
pyxel_input_manager/analog_processor.py
pyxel_input_manager/demo.py
pyxel_input_manager/demo_analog.py
pyxel_input_manager/input_bindings.py
pyxel_input_manager/input_event.py
pyxel_input_manager/input_map.py
pyxel_input_manager/input_types.py
pyxel_input_manager/state_manager.py
pyxel_input_manager-0.1.2.dist-info/LICENSE
pyxel_input_manager-0.1.2.dist-info/METADATA
pyxel_input_manager-0.1.2.dist-info/WHEEL
pyxel_input_manager-0.1.2.dist-info/entry_points.txt
pyxel_input_manager-0.1.2.dist-info/top_level.txt
pyxel_input_manager-0.1.2.dist-info/RECORD
