Metadata-Version: 2.1
Name: pyxel-input-manager
Version: 0.1.2
Summary: A simple input manager for Pyxel
Author: Tomonobu Terakubo
Maintainer: Tomonobu Terakubo
License: MIT License
Project-URL: homepage, https://github.com/2b3d4f/pyxel-input-manager
Project-URL: repository, https://github.com/2b3d4f/pyxel-input-manager
Project-URL: issues, https://github.com/2b3d4f/pyxel-input-manager/issues
Classifier: Development Status :: 3 - Alpha
Classifier: Intended Audience :: Developers
Classifier: License :: OSI Approved :: MIT License
Classifier: Programming Language :: Python :: 3
Requires-Python: >=3.11
License-File: LICENSE
Requires-Dist: pyxel>=2.2.8
